imgdt/__init__.py
imgdt/imgdt.py
imgdt/tools.py
imgdt/utils.py
imgdt-0.0.4.dist-info/AUTHORS
imgdt-0.0.4.dist-info/LICENSE.txt
imgdt-0.0.4.dist-info/METADATA
imgdt-0.0.4.dist-info/WHEEL
imgdt-0.0.4.dist-info/top_level.txt
imgdt-0.0.4.dist-info/RECORD
