Metadata-Version: 2.1
Name: imgdt
Version: 0.0.4
Summary: ImageDatasetTools is a Python library used to setup a dataset of images
Home-page: https://github.com/MikiTwenty/imgdt
Author: Michele Ventimiglia
Author-email: michele.ventimiglia01@gmail.com
License: MIT
Classifier: Development Status :: 4 - Beta
Classifier: Intended Audience :: Developers
Classifier: License :: OSI Approved :: MIT License
Classifier: Operating System :: OS Independent
Classifier: Programming Language :: Python
Classifier: Programming Language :: Python :: 3
Classifier: Programming Language :: Python :: 3.7
Classifier: Programming Language :: Python :: 3.8
Classifier: Programming Language :: Python :: 3.9
Classifier: Programming Language :: Python :: 3.10
Classifier: Programming Language :: Python :: 3.11
Requires-Python: >=3.7
License-File: LICENSE.txt
License-File: AUTHORS
Requires-Dist: Pillow
